vicksclass/__init__.py
vicksclass/vicks.py
vickclass-0.0.1.dist-info/METADATA
vickclass-0.0.1.dist-info/WHEEL
vickclass-0.0.1.dist-info/top_level.txt
vickclass-0.0.1.dist-info/RECORD
